mocca2/__init__.py
mocca2/__main__.py
mocca2/exceptions.py
mocca2/math.py
mocca2/py.typed
mocca2/serializing.py
mocca2/baseline/__init__.py
mocca2/baseline/arpls.py
mocca2/baseline/asls.py
mocca2/baseline/flatfit.py
mocca2/baseline/wrapper.py
mocca2/classes/__init__.py
mocca2/classes/chromatogram.py
mocca2/classes/component.py
mocca2/classes/compound.py
mocca2/classes/data2d.py
mocca2/classes/deconvolved_peak.py
mocca2/classes/peak.py
mocca2/clustering/__init__.py
mocca2/clustering/cluster_components.py
mocca2/dataset/__init__.py
mocca2/dataset/dataset.py
mocca2/dataset/settings.py
mocca2/deconvolution/__init__.py
mocca2/deconvolution/alternating_lstsq.py
mocca2/deconvolution/deconvolve.py
mocca2/deconvolution/fit_peak_model.py
mocca2/deconvolution/guess_spectra.py
mocca2/deconvolution/nnls.py
mocca2/deconvolution/nonnegative_lstsq.py
mocca2/deconvolution/peak_models.py
mocca2/example_data/__init__.py
mocca2/example_data/downloader.py
mocca2/example_data/loaders.py
mocca2/parsers/__init__.py
mocca2/parsers/chemstation.py
mocca2/parsers/empower.py
mocca2/parsers/labsolutions.py
mocca2/parsers/masslynx.py
mocca2/parsers/wrapper.py
mocca2/peaks/__init__.py
mocca2/peaks/find_peaks.py
mocca2/peaks/merge_overlapping.py
mocca2/peaks/split.py
mocca2-0.1.18.dist-info/licenses/LICENSE.txt
mocca2-0.1.18.dist-info/METADATA
mocca2-0.1.18.dist-info/WHEEL
mocca2-0.1.18.dist-info/top_level.txt
mocca2-0.1.18.dist-info/RECORD
