Metadata-Version: 2.4
Name: mocca2
Version: 0.1.18
Summary: MOCCA2 is an open-source Python project to analyze HPLC-DAD raw data
Author-email: Jan Oboril <jan.oboril@gmail.com>
Project-URL: Homepage, https://bayer-group.github.io/MOCCA/
Project-URL: Issues, https://github.com/bayer-group/MOCCA/issues
Classifier: Programming Language :: Python :: 3
Classifier: License :: OSI Approved :: MIT License
Classifier: Operating System :: OS Independent
Requires-Python: >=3.10
License-File: LICENSE.txt
Requires-Dist: numpy>1.20
Requires-Dist: scipy>1.10
Requires-Dist: scikit-learn>1.3
Requires-Dist: pyyaml>6.0
Requires-Dist: pandas>2.1
Requires-Dist: matplotlib>3.6
Requires-Dist: pyarrow>15.0
Requires-Dist: rainbow-api>1.0
Dynamic: license-file
